zope.testing-5.0.1-py3.9-nspkg.pth
zope/testing/__init__.py
zope/testing/cleanup.py
zope/testing/cleanup.txt
zope/testing/doctestcase.py
zope/testing/doctestcase.txt
zope/testing/exceptions.py
zope/testing/formparser.py
zope/testing/formparser.txt
zope/testing/loggingsupport.py
zope/testing/loggingsupport.txt
zope/testing/module.py
zope/testing/module.txt
zope/testing/renormalizing.py
zope/testing/renormalizing.txt
zope/testing/setupstack.py
zope/testing/setupstack.txt
zope/testing/test-1.txt
zope/testing/test4.txt
zope/testing/test4e.txt
zope/testing/test4f.txt
zope/testing/testrunner.py
zope/testing/tests.py
zope/testing/wait.py
zope/testing/wait.txt
zope.testing-5.0.1.dist-info/LICENSE.txt
zope.testing-5.0.1.dist-info/METADATA
zope.testing-5.0.1.dist-info/WHEEL
zope.testing-5.0.1.dist-info/namespace_packages.txt
zope.testing-5.0.1.dist-info/top_level.txt
zope.testing-5.0.1.dist-info/RECORD
